Metadata-Version: 2.1
Name: unzip-rename
Version: 0.0.1
Summary: Extract zip file and rename all files base on 'cp437' codec.
Home-page: https://makerbean.com
Author: MakerBi
Author-email: andersonby@163.com
License: UNKNOWN
Platform: UNKNOWN
Classifier: Programming Language :: Python :: 3
Classifier: License :: OSI Approved :: MIT License
Classifier: Operating System :: OS Independent
Requires-Python: >=3.6
